fdhpy/__init__.py
fdhpy/_saveme_notes.py
fdhpy/_working.py
fdhpy/chiou_et_al_2025.py
fdhpy/cli.py
fdhpy/fault_displacement_model.py
fdhpy/fault_displacement_model_variables.py
fdhpy/kuehn_et_al_2024.py
fdhpy/lavrentiadis_abrahamson_2023.py
fdhpy/loglinear_scaling_model.py
fdhpy/moss_et_al_2024.py
fdhpy/moss_ross_2011.py
fdhpy/normalized_fault_displacement_model.py
fdhpy/petersen_et_al_2011.py
fdhpy/utils.py
fdhpy/youngs_et_al_2003.py
fdhpy/data/chiou_2025_coefficients.csv
fdhpy/data/kuehn_2024_coefficients_posterior_NM_powtr.csv
fdhpy/data/kuehn_2024_coefficients_posterior_REV_powtr.csv
fdhpy/data/kuehn_2024_coefficients_posterior_SS_powtr.csv
fdhpy/data/kuehn_2024_uncertainty_NM.csv
fdhpy/data/kuehn_2024_uncertainty_REV.csv
fdhpy/data/kuehn_2024_uncertainty_SS.csv
fdhpy/data/lavrentiadis_2023_coefficients.csv
fdhpy/data/moss_2024_gamma_distribution_parameters_d_ad.csv
fdhpy/data/moss_2024_gamma_distribution_parameters_d_md.csv
fdhpy-1.0.2.dist-info/licenses/AUTHORS.rst
fdhpy-1.0.2.dist-info/licenses/LICENSE
fdhpy-1.0.2.dist-info/METADATA
fdhpy-1.0.2.dist-info/WHEEL
fdhpy-1.0.2.dist-info/entry_points.txt
fdhpy-1.0.2.dist-info/top_level.txt
fdhpy-1.0.2.dist-info/RECORD
