Metadata-Version: 2.4
Name: fdhpy
Version: 1.0.2
Summary: Implementations of FDHI Project Fault Displacement Models
Author-email: Alex Sarmiento <asarmy@ucla.edu>
License: MIT
Project-URL: repository, https://github.com/asarmy/fdhpy
Project-URL: homepage, https://github.com/NHR3-UCLA/FDHI_FDM
Keywords: fault displacement,seismic hazard,fdhpy
Requires-Python: >=3.8
License-File: LICENSE
License-File: AUTHORS.rst
Requires-Dist: numpy
Requires-Dist: pandas
Requires-Dist: scipy
Requires-Dist: attrs>=24.2.0
Provides-Extra: examples
Requires-Dist: jupyter; extra == "examples"
Requires-Dist: matplotlib; extra == "examples"
Requires-Dist: statsmodels; extra == "examples"
Provides-Extra: dev
Requires-Dist: pytest; extra == "dev"
Requires-Dist: pytest-cov; extra == "dev"
Requires-Dist: black; extra == "dev"
Requires-Dist: flake8; extra == "dev"
Requires-Dist: twine; extra == "dev"
Requires-Dist: sphinx; extra == "dev"
Requires-Dist: sphinx_rtd_theme; extra == "dev"
Requires-Dist: sphinxcontrib-bibtex; extra == "dev"
Requires-Dist: pydocstyle; extra == "dev"
Requires-Dist: myst-parser; extra == "dev"
Requires-Dist: pre-commit; extra == "dev"
Requires-Dist: toml; extra == "dev"
Requires-Dist: build; extra == "dev"
Dynamic: license-file
